finance_report/__init__.py
finance_report/__main__.py
finance_report/report_generator.py
finance_report_owttsair-0.1.0.dist-info/METADATA
finance_report_owttsair-0.1.0.dist-info/WHEEL
finance_report_owttsair-0.1.0.dist-info/top_level.txt
finance_report_owttsair-0.1.0.dist-info/RECORD
